AUTHORS
LICENSE
MANIFEST.in
README.rst
setup.py
example/__init__.py
example/settings.py
example/api/__init__.py
example/api/urls.py
example/api/resources/__init__.py
example/api/resources/identity.py
example/api/serializers/__init__.py
example/api/serializers/identity.py
example/api/serializers/post.py
example/tests/__init__.py
example/tests/test_format_keys.py
example/tests/test_generic_viewset.py
example/tests/test_model_viewsets.py
example/tests/test_multiple_id_mixin.py
example/tests/test_sideload_resources.py
rest_framework_ember/__init__.py
rest_framework_ember/mixins.py
rest_framework_ember/pagination.py
rest_framework_ember/parsers.py
rest_framework_ember/renderers.py
rest_framework_ember/utils.py
rest_framework_ember.egg-info/PKG-INFO
rest_framework_ember.egg-info/SOURCES.txt
rest_framework_ember.egg-info/dependency_links.txt
rest_framework_ember.egg-info/requires.txt
rest_framework_ember.egg-info/top_level.txt