Metadata-Version: 1.1
Name: rest-framework-ember
Version: 1.2.0
Summary: Make EmberJS and Django Rest Framework play nice together. Follows jsonapi.org spec
Home-page: https://github.com/ngenworks/rest_framework_ember
Author: nGen Works
Author-email: tech@ngenworks.com
License: BSD
Keywords: EmberJS Django REST
Platform: any
Classifier: Development Status :: 4 - Beta
Classifier: Framework :: Django
Classifier: Environment :: Web Environment
Classifier: License :: OSI Approved :: BSD License
Classifier: Intended Audience :: Developers
Classifier: Programming Language :: Python
Classifier: Programming Language :: Python :: 2.6
Classifier: Programming Language :: Python :: 2.7
Classifier: Topic :: Software Development :: Libraries :: Application Frameworks
Classifier: Topic :: Software Development :: Libraries :: Python Modules
